<?xml version="1.0" encoding="iso-8859-1"?>
<data>	
	<slide>	
		<element type="IMAGE" x="0" y="0" width="680" height="490" src="../../../common/images/page_backgrounds/bg_topolgy_multislide.jpg" />
<element type="IMAGE" src="media_3.4.1.1.png" x="0" y="0" width="680" height="490"/>
<element type="TEXT" subType="TITLE" compId="ID_title"/>

<element type="TEXT" compId="ID_txt01" x="244" y="147" width="209" expand="up" align="center" />
<element type="TEXT" compId="ID_txt02" x="253" y="199" width="192" expand="up+down" align="center" />
<element type="TEXT" compId="ID_txt03" x="347" y="331" width="192" expand="up" align="center" />
<element type="TEXT" compId="ID_txt04" x="82" y="390" width="67" expand="up+down" align="center" color="#ffffff" />
<element type="TEXT" compId="ID_txt05" x="178" y="390" width="68" expand="up+down" align="center" color="#ffffff" />
<element type="TEXT" compId="ID_txt06" x="274" y="390" width="93" expand="up+down" align="center" color="#ffffff" />
<element type="TEXT" compId="ID_txt07" x="391" y="390" width="93" expand="up+down" align="center" color="#ffffff" />
<element type="TEXT" compId="ID_txt08" x="510" y="390" width="93" expand="up+down" align="center" color="#ffffff" />
	</slide>
</data>